{
  "version": 1,
  "runId": "2026-03-20T08-47-03-927Z_1da02a",
  "captured": true,
  "capturedAt": "2026-03-20T08:47:03.938Z",
  "domains": {
    "files": {
      "supported": true,
      "verifyDefault": "ok"
    },
    "workspace": {
      "supported": true,
      "verifyDefault": "ok"
    },
    "database": {
      "supported": false,
      "verifyDefault": "not_checked"
    },
    "environment": {
      "supported": false,
      "verifyDefault": "not_checked"
    },
    "server": {
      "supported": false,
      "verifyDefault": "not_checked"
    }
  }
}
